[
	{
		"__TYPE__": "SharedSliceContent",
		"variation": "default",
		"primary": {
			"heading": {
				"__TYPE__": "StructuredTextContent",
				"value": [
					{
						"type": "heading2",
						"content": {
							"text": "Division"
						}
					}
				]
			}
		},
		"items": [
			{
				"__TYPE__": "GroupItemContent",
				"value": [
					[
						"icon",
						{
							"__TYPE__": "FieldContent",
							"value": "bargraph",
							"type": "Select"
						}
					],
					[
						"title",
						{
							"__TYPE__": "StructuredTextContent",
							"value": [
								{
									"type": "heading3",
									"content": {
										"text": "During"
									}
								}
							]
						}
					],
					[
						"description",
						{
							"__TYPE__": "StructuredTextContent",
							"value": [
								{
									"type": "paragraph",
									"content": {
										"text": "Ut mollit sint sit sit in eiusmod aliquip labore consequat occaecat velit veniam anim. Nostrud ex eu officia enim pariatur sit magna. Ad reprehenderit sunt veniam deserunt."
									}
								}
							]
						}
					]
				]
			},
			{
				"__TYPE__": "GroupItemContent",
				"value": [
					[
						"icon",
						{
							"__TYPE__": "FieldContent",
							"type": "Select",
							"value": "clover"
						}
					],
					[
						"description",
						{
							"__TYPE__": "StructuredTextContent",
							"value": [
								{
									"type": "paragraph",
									"content": {
										"text": "Ut mollit sint sit sit in eiusmod aliquip labore consequat occaecat velit veniam anim. Nostrud ex eu officia enim pariatur sit magna. Ad reprehenderit sunt veniam deserunt.",
										"spans": []
									},
									"direction": "ltr"
								}
							]
						}
					],
					[
						"title",
						{
							"__TYPE__": "StructuredTextContent",
							"value": [
								{
									"type": "heading3",
									"content": {
										"text": "Test",
										"spans": []
									},
									"direction": "ltr"
								}
							]
						}
					]
				]
			},
			{
				"__TYPE__": "GroupItemContent",
				"value": [
					[
						"icon",
						{
							"__TYPE__": "FieldContent",
							"type": "Select",
							"value": "hourglass"
						}
					],
					[
						"title",
						{
							"__TYPE__": "StructuredTextContent",
							"value": [
								{
									"type": "heading3",
									"content": {
										"text": "Test",
										"spans": []
									},
									"direction": "ltr"
								}
							]
						}
					],
					[
						"description",
						{
							"__TYPE__": "StructuredTextContent",
							"value": [
								{
									"type": "paragraph",
									"content": {
										"text": "Ut mollit sint sit sit in eiusmod aliquip labore consequat occaecat velit veniam anim. Nostrud ex eu officia enim pariatur sit magna. Ad reprehenderit sunt veniam deserunt.",
										"spans": []
									},
									"direction": "ltr"
								}
							]
						}
					]
				]
			},
			{
				"__TYPE__": "GroupItemContent",
				"value": [
					[
						"icon",
						{
							"__TYPE__": "FieldContent",
							"type": "Select",
							"value": "calendar"
						}
					],
					[
						"title",
						{
							"__TYPE__": "StructuredTextContent",
							"value": [
								{
									"type": "heading3",
									"content": {
										"text": "Test",
										"spans": []
									},
									"direction": "ltr"
								}
							]
						}
					],
					[
						"description",
						{
							"__TYPE__": "StructuredTextContent",
							"value": [
								{
									"type": "paragraph",
									"content": {
										"text": "Ut mollit sint sit sit in eiusmod aliquip labore consequat occaecat velit veniam anim. Nostrud ex eu officia enim pariatur sit magna. Ad reprehenderit sunt veniam deserunt.",
										"spans": []
									},
									"direction": "ltr"
								}
							]
						}
					]
				]
			}
		]
	}
]